LICENSE
README.md
setup.cfg
setup.py
vectors2d/__init__.py
vectors2d/vectors2d.py
vectors2d.egg-info/PKG-INFO
vectors2d.egg-info/SOURCES.txt
vectors2d.egg-info/dependency_links.txt
vectors2d.egg-info/top_level.txt