Metadata-Version: 2.1
Name: vectors2d
Version: 1.0.0
Summary: Small but useful module that allows to work with vectors in 2-dimensional space.
Home-page: https://github.com/MitryP/vectors
Author: Dmitry Popov
Author-email: thedmitryp@ukr.net
License: MIT
Download-URL: https://github.com/MitryP/vectors/archive/1.0.0.tar.gz
Keywords: vectors,2-dimensional,flat,coordinates,open-source
Platform: UNKNOWN
Classifier: Development Status :: 5 - Production/Stable
Classifier: Intended Audience :: Developers
Classifier: Topic :: Software Development
Classifier: Topic :: Software Development :: Build Tools
Classifier: Topic :: Software Development :: Libraries
Classifier: Topic :: Software Development :: Libraries :: Python Modules
Classifier: License :: OSI Approved :: MIT License
Classifier: Programming Language :: Python :: 3
Classifier: Programming Language :: Python :: 3.4
Classifier: Programming Language :: Python :: 3.5
Classifier: Programming Language :: Python :: 3.6
Classifier: Programming Language :: Python :: 3.7
Classifier: Programming Language :: Python :: 3.8
Classifier: Programming Language :: Python :: 3.9
